Metadata-Version: 1.0
Name: datacubesdk
Version: 0.1.0
Summary: Datacube tools and scripts
Home-page: https://github.com/AllenInstitute/DatacubeSDK.git
Author: Chris Barber
Author-email: chrisba@alleninstitute.org
License: UNKNOWN
Platform: UNKNOWN
